netbox_aci_plugin/__init__.py
netbox_aci_plugin/choices.py
netbox_aci_plugin/constants.py
netbox_aci_plugin/navigation.py
netbox_aci_plugin/search.py
netbox_aci_plugin/urls.py
netbox_aci_plugin/validators.py
netbox_aci_plugin/api/__init__.py
netbox_aci_plugin/api/urls.py
netbox_aci_plugin/api/views.py
netbox_aci_plugin/api/serializers/__init__.py
netbox_aci_plugin/api/serializers/fabric/__init__.py
netbox_aci_plugin/api/serializers/fabric/fabrics.py
netbox_aci_plugin/api/serializers/fabric/nodes.py
netbox_aci_plugin/api/serializers/fabric/pods.py
netbox_aci_plugin/api/serializers/tenant/__init__.py
netbox_aci_plugin/api/serializers/tenant/app_profiles.py
netbox_aci_plugin/api/serializers/tenant/bridge_domains.py
netbox_aci_plugin/api/serializers/tenant/contract_filters.py
netbox_aci_plugin/api/serializers/tenant/contracts.py
netbox_aci_plugin/api/serializers/tenant/endpoint_groups.py
netbox_aci_plugin/api/serializers/tenant/endpoint_security_groups.py
netbox_aci_plugin/api/serializers/tenant/tenants.py
netbox_aci_plugin/api/serializers/tenant/vrfs.py
netbox_aci_plugin/filtersets/__init__.py
netbox_aci_plugin/filtersets/mixins.py
netbox_aci_plugin/filtersets/fabric/__init__.py
netbox_aci_plugin/filtersets/fabric/fabrics.py
netbox_aci_plugin/filtersets/fabric/nodes.py
netbox_aci_plugin/filtersets/fabric/pods.py
netbox_aci_plugin/filtersets/tenant/__init__.py
netbox_aci_plugin/filtersets/tenant/app_profiles.py
netbox_aci_plugin/filtersets/tenant/bridge_domains.py
netbox_aci_plugin/filtersets/tenant/contract_filters.py
netbox_aci_plugin/filtersets/tenant/contracts.py
netbox_aci_plugin/filtersets/tenant/endpoint_groups.py
netbox_aci_plugin/filtersets/tenant/endpoint_security_groups.py
netbox_aci_plugin/filtersets/tenant/tenants.py
netbox_aci_plugin/filtersets/tenant/vrfs.py
netbox_aci_plugin/forms/__init__.py
netbox_aci_plugin/forms/fabric/__init__.py
netbox_aci_plugin/forms/fabric/fabrics.py
netbox_aci_plugin/forms/fabric/nodes.py
netbox_aci_plugin/forms/fabric/pods.py
netbox_aci_plugin-0.2.0.dist-info/licenses/LICENSE
netbox_aci_plugin-0.2.0.dist-info/METADATA
netbox_aci_plugin-0.2.0.dist-info/WHEEL
netbox_aci_plugin-0.2.0.dist-info/top_level.txt
netbox_aci_plugin-0.2.0.dist-info/RECORD
