Metadata-Version: 2.4
Name: netbox-aci-plugin
Version: 0.2.0
Summary: NetBox plugin for Cisco ACI
Author-email: Martin Hauser <git@pheus.dev>
Maintainer-email: Martin Hauser <git@pheus.dev>
License-Expression: GPL-3.0-or-later
Project-URL: Homepage, https://github.com/pheus/netbox-aci-plugin
Project-URL: Documentation, https://pheus.github.io/netbox-aci-plugin/
Project-URL: Source, https://github.com/pheus/netbox-aci-plugin
Project-URL: Issues, https://github.com/pheus/netbox-aci-plugin/issues
Project-URL: Changelog, https://github.com/pheus/netbox-aci-plugin/releases
Keywords: netbox,netbox-plugin,cisco,aci
Classifier: Development Status :: 3 - Alpha
Classifier: Framework :: Django
Classifier: Framework :: Django :: 5.2
Classifier: Intended Audience :: Developers
Classifier: Intended Audience :: System Administrators
Classifier: Natural Language :: English
Classifier: Operating System :: OS Independent
Classifier: Programming Language :: Python
Classifier: Programming Language :: Python :: 3
Classifier: Programming Language :: Python :: 3 :: Only
Classifier: Programming Language :: Python :: 3.12
Classifier: Programming Language :: Python :: 3.13
Classifier: Programming Language :: Python :: 3.14
Requires-Python: >=3.12.0
License-File: LICENSE
Provides-Extra: docs
Requires-Dist: mkdocs==1.6.1; extra == "docs"
Requires-Dist: mkdocs-material==9.7.1; extra == "docs"
Requires-Dist: mkdocs-include-markdown-plugin==7.2.1; extra == "docs"
Provides-Extra: test
Requires-Dist: check-manifest==0.51; extra == "test"
Requires-Dist: pre-commit==4.5.1; extra == "test"
Requires-Dist: pytest==9.0.2; extra == "test"
Requires-Dist: ruff==0.14.14; extra == "test"
Requires-Dist: yamllint==1.38.0; extra == "test"
Dynamic: license-file
